[
    {"country": "Afghanistan", "key": "AF"},
    {"country": "Albania", "key": "AL"},
    {"country": "Algeria", "key": "DZ"},
    {"country": "Andorra", "key": "AD"},
    {"country": "Angola", "key": "AO"},
    {"country": "Antigua and Barbuda", "key": "AG"},
    {"country": "Argentina", "key": "AR"},
    {"country": "Armenia", "key": "AM"},
    {"country": "Australia", "key": "AU"},
    {"country": "Austria", "key": "AT"},
    {"country": "Azerbaijan", "key": "AZ"},
    {"country": "Bahamas", "key": "BS"},
    {"country": "Bahrain", "key": "BH"},
    {"country": "Bangladesh", "key": "BD"},
    {"country": "Barbados", "key": "BB"},
    {"country": "Belarus", "key": "BY"},
    {"country": "Belgium", "key": "BE"},
    {"country": "Belize", "key": "BZ"},
    {"country": "Benin", "key": "BJ"},
    {"country": "Bhutan", "key": "BT"},
    {"country": "Bolivia", "key": "BO"},
    {"country": "Bosnia and Herzegovina", "key": "BA"},
    {"country": "Botswana", "key": "BW"},
    {"country": "Brazil", "key": "BR"},
    {"country": "Brunei Darussalam", "key": "BN"},
    {"country": "Bulgaria", "key": "BG"},
    {"country": "Burkina Faso", "key": "BF"},
    {"country": "Burundi", "key": "BI"},
    {"country": "Cabo Verde", "key": "CV"},
    {"country": "Cambodia", "key": "KH"},
    {"country": "Cameroon", "key": "CM"},
    {"country": "Canada", "key": "CA"},
    {"country": "Central African Republic", "key": "CF"},
    {"country": "Chad", "key": "TD"},
    {"country": "Chile", "key": "CL"},
    {"country": "China", "key": "CN"},
    {"country": "Colombia", "key": "CO"},
    {"country": "Comoros", "key": "KM"},
    {"country": "Congo (Congo-Brazzaville)", "key": "CG"},
    {"country": "Costa Rica", "key": "CR"},
    {"country": "Croatia", "key": "HR"},
    {"country": "Cuba", "key": "CU"},
    {"country": "Cyprus", "key": "CY"},
    {"country": "Czech Republic", "key": "CZ"},
    {"country": "Democratic Republic of the Congo", "key": "CD"},
    {"country": "Denmark", "key": "DK"},
    {"country": "Djibouti", "key": "DJ"},
    {"country": "Dominica", "key": "DM"},
    {"country": "Dominican Republic", "key": "DO"},
    {"country": "Ecuador", "key": "EC"},
    {"country": "Egypt", "key": "EG"},
    {"country": "El Salvador", "key": "SV"},
    {"country": "Equatorial Guinea", "key": "GQ"},
    {"country": "Eritrea", "key": "ER"},
    {"country": "Estonia", "key": "EE"},
    {"country": "Eswatini", "key": "SZ"},
    {"country": "Ethiopia", "key": "ET"},
    {"country": "Fiji", "key": "FJ"},
    {"country": "Finland", "key": "FI"},
    {"country": "France", "key": "FR"},
    {"country": "Gabon", "key": "GA"},
    {"country": "Gambia", "key": "GM"},
    {"country": "Georgia", "key": "GE"},
    {"country": "Germany", "key": "DE"},
    {"country": "Ghana", "key": "GH"},
    {"country": "Greece", "key": "GR"},
    {"country": "Grenada", "key": "GD"},
    {"country": "Guatemala", "key": "GT"},
    {"country": "Guinea", "key": "GN"},
    {"country": "Guinea-Bissau", "key": "GW"},
    {"country": "Guyana", "key": "GY"},
    {"country": "Haiti", "key": "HT"},
    {"country": "Honduras", "key": "HN"},
    {"country": "Hungary", "key": "HU"},
    {"country": "Iceland", "key": "IS"},
    {"country": "India", "key": "IN"},
    {"country": "Indonesia", "key": "ID"},
    {"country": "Iran", "key": "IR"},
    {"country": "Iraq", "key": "IQ"},
    {"country": "Ireland", "key": "IE"},
    {"country": "Israel", "key": "IL"},
    {"country": "Italy", "key": "IT"},
    {"country": "Jamaica", "key": "JM"},
    {"country": "Japan", "key": "JP"},
    {"country": "Jordan", "key": "JO"},
    {"country": "Kazakhstan", "key": "KZ"},
    {"country": "Kenya", "key": "KE"},
    {"country": "Kiribati", "key": "KI"},
    {"country": "Kuwait", "key": "KW"},
    {"country": "Kyrgyzstan", "key": "KG"},
    {"country": "Laos", "key": "LA"},
    {"country": "Latvia", "key": "LV"},
    {"country": "Lebanon", "key": "LB"},
    {"country": "Lesotho", "key": "LS"},
    {"country": "Liberia", "key": "LR"},
    {"country": "Libya", "key": "LY"},
    {"country": "Liechtenstein", "key": "LI"},
    {"country": "Lithuania", "key": "LT"},
    {"country": "Luxembourg", "key": "LU"},
    {"country": "Madagascar", "key": "MG"},
    {"country": "Malawi", "key": "MW"},
    {"country": "Malaysia", "key": "MY"},
    {"country": "Maldives", "key": "MV"},
    {"country": "Mali", "key": "ML"},
    {"country": "Malta", "key": "MT"},
    {"country": "Marshall Islands", "key": "MH"},
    {"country": "Mauritania", "key": "MR"},
    {"country": "Mauritius", "key": "MU"},
    {"country": "Mexico", "key": "MX"},
    {"country": "Micronesia", "key": "FM"},
    {"country": "Moldova", "key": "MD"},
    {"country": "Monaco", "key": "MC"},
    {"country": "Mongolia", "key": "MN"},
    {"country": "Montenegro", "key": "ME"},
    {"country": "Morocco", "key": "MA"},
    {"country": "Mozambique", "key": "MZ"},
    {"country": "Myanmar (Burma)", "key": "MM"},
    {"country": "Namibia", "key": "NA"},
    {"country": "Nauru", "key": "NR"},
    {"country": "Nepal", "key": "NP"},
    {"country": "Netherlands", "key": "NL"},
    {"country": "New Zealand", "key": "NZ"},
    {"country": "Nicaragua", "key": "NI"},
    {"country": "Niger", "key": "NE"},
    {"country": "Nigeria", "key": "NG"},
    {"country": "North Korea", "key": "KP"},
    {"country": "North Macedonia", "key": "MK"},
    {"country": "Norway", "key": "NO"},
    {"country": "Oman", "key": "OM"},
    {"country": "Pakistan", "key": "PK"},
    {"country": "Palau", "key": "PW"},
    {"country": "Palestine", "key": "PS"},
    {"country": "Panama", "key": "PA"},
    {"country": "Papua New Guinea", "key": "PG"},
    {"country": "Paraguay", "key": "PY"},
    {"country": "Peru", "key": "PE"},
    {"country": "Philippines", "key": "PH"},
    {"country": "Poland", "key": "PL"},
    {"country": "Portugal", "key": "PT"},
    {"country": "Qatar", "key": "QA"},
    {"country": "Romania", "key": "RO"},
    {"country": "Russia", "key": "RU"},
    {"country": "Rwanda", "key": "RW"},
    {"country": "Saint Kitts and Nevis", "key": "KN"},
    {"country": "Saint Lucia", "key": "LC"},
    {"country": "Saint Vincent and the Grenadines", "key": "VC"},
    {"country": "Samoa", "key": "WS"},
    {"country": "San Marino", "key": "SM"},
    {"country": "Sao Tome and Principe", "key": "ST"},
    {"country": "Saudi Arabia", "key": "SA"},
    {"country": "Senegal", "key": "SN"},
    {"country": "Serbia", "key": "RS"},
    {"country": "Seychelles", "key": "SC"},
    {"country": "Sierra Leone", "key": "SL"},
    {"country": "Singapore", "key": "SG"},
    {"country": "Slovakia", "key": "SK"},
    {"country": "Slovenia", "key": "SI"},
    {"country": "Solomon Islands", "key": "SB"},
    {"country": "Somalia", "key": "SO"},
    {"country": "South Africa", "key": "ZA"},
    {"country": "South Korea", "key": "KR"},
    {"country": "South Sudan", "key": "SS"},
    {"country": "Spain", "key": "ES"},
    {"country": "Sri Lanka", "key": "LK"},
    {"country": "Sudan", "key": "SD"},
    {"country": "Suriname", "key": "SR"},
    {"country": "Sweden", "key": "SE"},
    {"country": "Switzerland", "key": "CH"},
    {"country": "Syria", "key": "SY"},
    {"country": "Tajikistan", "key": "TJ"},
    {"country": "Tanzania", "key": "TZ"},
    {"country": "Thailand", "key": "TH"},
    {"country": "Timor-Leste", "key": "TL"},
    {"country": "Togo", "key": "TG"},
    {"country": "Tonga", "key": "TO"},
    {"country": "Trinidad and Tobago", "key": "TT"},
    {"country": "Tunisia", "key": "TN"},
    {"country": "Turkey", "key": "TR"},
    {"country": "Turkmenistan", "key": "TM"},
    {"country": "Tuvalu", "key": "TV"},
    {"country": "Uganda", "key": "UG"},
    {"country": "Ukraine", "key": "UA"},
    {"country": "United Arab Emirates", "key": "AE"},
    {"country": "United Kingdom", "key": "GB"},
    {"country": "United States", "key": "US"},
    {"country": "Uruguay", "key": "UY"},
    {"country": "Uzbekistan", "key": "UZ"},
    {"country": "Vanuatu", "key": "VU"},
    {"country": "Vatican City", "key": "VA"},
    {"country": "Venezuela", "key": "VE"},
    {"country": "Vietnam", "key": "VN"},
    {"country": "Yemen", "key": "YE"},
    {"country": "Zambia", "key": "ZM"},
    {"country": "Zimbabwe", "key": "ZW"}
]
   
  